cli/__init__.py
cli/audit.py
cli/config.py
cli/cust_measures.py
cli/findings_export.py
cli/findings_sync.py
cli/housekeeper.py
cli/loc.py
cli/measures_export.py
cli/options.py
cli/projects_cli.py
cli/projects_export.py
cli/projects_import.py
cli/rules_cli.py
cli/support.py
migration/__init__.py
migration/migration.py
sonar/__init__.py
sonar/aggregations.py
sonar/app_branches.py
sonar/applications.py
sonar/branches.py
sonar/changelog.py
sonar/components.py
sonar/custom_measures.py
sonar/devops.py
sonar/errcodes.py
sonar/exceptions.py
sonar/findings.py
sonar/groups.py
sonar/hotspots.py
sonar/issues.py
sonar/languages.py
sonar/logging.py
sonar/measures.py
sonar/metrics.py
sonar/organizations.py
sonar/platform.py
sonar/portfolio_reference.py
sonar/portfolios.py
sonar/projects.py
sonar/pull_requests.py
sonar/qualitygates.py
sonar/qualityprofiles.py
sonar/rules.py
sonar/settings.py
sonar/sif.py
sonar/sif_node.py
sonar/sqobject.py
sonar/syncer.py
sonar/tasks.py
sonar/tokens.py
sonar/users.py
sonar/utilities.py
sonar/version.py
sonar/webhooks.py
sonar/audit/__init__.py
sonar/audit/config.py
sonar/audit/problem.py
sonar/audit/rules.json
sonar/audit/rules.py
sonar/audit/severities.py
sonar/audit/sonar-audit.properties
sonar/audit/types.py
sonar/dce/__init__.py
sonar/dce/app_nodes.py
sonar/dce/nodes.py
sonar/dce/search_nodes.py
sonar/permissions/__init__.py
sonar/permissions/aggregation_permissions.py
sonar/permissions/application_permissions.py
sonar/permissions/global_permissions.py
sonar/permissions/permission_templates.py
sonar/permissions/permissions.py
sonar/permissions/portfolio_permissions.py
sonar/permissions/project_permissions.py
sonar/permissions/quality_permissions.py
sonar/permissions/qualitygate_permissions.py
sonar/permissions/qualityprofile_permissions.py
sonar/permissions/template_permissions.py
sonar/util/__init__.py
sonar/util/types.py
sonar_migration-0.4.data/scripts/sonar-tools
sonar_migration-0.4.data/scripts/sonar_migration
sonar_migration-0.4.dist-info/LICENSE
sonar_migration-0.4.dist-info/METADATA
sonar_migration-0.4.dist-info/WHEEL
sonar_migration-0.4.dist-info/entry_points.txt
sonar_migration-0.4.dist-info/top_level.txt
sonar_migration-0.4.dist-info/RECORD
