Metadata-Version: 2.1
Name: sonar-migration
Version: 0.4
Summary: A SonarQube collection tool to use in the context of SonarQube to SonarCloud migration
Home-page: https://github.com/okorach/sonar-tools
Author: Olivier Korach
Author-email: olivier.korach@gmail.com
Project-URL: Bug Tracker, https://github.com/okorach/sonar-tools/issues
Project-URL: Documentation, https://github.com/okorach/sonar-tools/migration/README.md
Project-URL: Source Code, https://github.com/okorach/sonar-tools
Classifier: Programming Language :: Python :: 3
Classifier: License :: OSI Approved :: GNU Lesser General Public License v3 or later (LGPLv3+)
Classifier: Operating System :: OS Independent
Requires-Python: >=3.8
License-File: LICENSE
Requires-Dist: argparse
Requires-Dist: datetime
Requires-Dist: python-dateutil
Requires-Dist: requests
Requires-Dist: jprops
